kiri_search/__init__.py
kiri_search/core.py
kiri_search/models/__init__.py
kiri_search/models/custom_models.py
kiri_search/models/models.py
kiri_search/models/tasks/__init__.py
kiri_search/models/tasks/base.py
kiri_search/models/tasks/classification.py
kiri_search/models/tasks/emotion.py
kiri_search/models/tasks/generation.py
kiri_search/models/tasks/qa.py
kiri_search/models/tasks/summarisation.py
kiri_search/models/tasks/vectorisation.py
kiri_search/search/__init__.py
kiri_search/search/documents.py
kiri_search/search/search.py
kiri_search/utils/__init__.py
kiri_search/utils/elastic.py
kiri_search/utils/processing.py
kiri_search/utils/verification.py
kirisearch-0.0.1.dist-info/LICENSE
kirisearch-0.0.1.dist-info/METADATA
kirisearch-0.0.1.dist-info/WHEEL
kirisearch-0.0.1.dist-info/top_level.txt
kirisearch-0.0.1.dist-info/RECORD
