Metadata-Version: 2.1
Name: kirisearch
Version: 0.0.1
Summary: Kiri Search
Home-page: https://github.com/kiri-ai/kiri-search
Author: Kiri OÜ
Author-email: hello@kiri.ai
License: UNKNOWN
Platform: UNKNOWN
Classifier: Programming Language :: Python :: 3
Classifier: License :: OSI Approved :: Apache Software License
Classifier: Operating System :: OS Independent
Requires-Python: >=3.6
Requires-Dist: elasticsearch
Requires-Dist: nltk
Requires-Dist: scipy
Requires-Dist: sentence-transformers
Requires-Dist: shortuuid
Requires-Dist: torch
Requires-Dist: transformers
